[
  {
    "key": "WWV",
    "label": "Equatorial warm-water volume anomaly",
    "unit": "standardized anomaly (production: NOAA PMEL TAO)",
    "source": "Seeded · production: NOAA PMEL TAO/TRITON",
    "update_frequency": "monthly",
    "provenance": "REFERENCE",
    "value": 0.8,
    "observed_at": "2026-05-15",
    "trend": "up"
  },
  {
    "key": "ENSO_PROB",
    "label": "El Niño probability (next season)",
    "unit": "% chance (production: NOAA CPC / IRI ENSO plume)",
    "source": "Seeded · production: dynamical forecast (NOAA CPC + IRI)",
    "update_frequency": "monthly",
    "provenance": "DEMO",
    "value": 62,
    "observed_at": "2026-05-15",
    "trend": "up"
  },
  {
    "key": "DYN_FORECAST",
    "label": "Projected ONI (next season)",
    "unit": "°C (production: dynamical forecast — CFSv2, ECMWF SEAS5)",
    "source": "Seeded · production: dynamical forecast (CFSv2, SEAS5)",
    "update_frequency": "monthly",
    "provenance": "DEMO",
    "value": 0.9,
    "observed_at": "2026-05-15",
    "trend": "up"
  }
]
